varphi_lsp_server/__init__.py
varphi_lsp_server/varphi_lsp_server.py
varphi_lsp_server-0.0.3.dist-info/LICENSE
varphi_lsp_server-0.0.3.dist-info/METADATA
varphi_lsp_server-0.0.3.dist-info/WHEEL
varphi_lsp_server-0.0.3.dist-info/entry_points.txt
varphi_lsp_server-0.0.3.dist-info/top_level.txt
varphi_lsp_server-0.0.3.dist-info/RECORD
