Metadata-Version: 2.1
Name: varphi_lsp_server
Version: 0.0.3
Summary: Language Server Protocol server for the Varphi Programming Language.
Home-page: https://github.com/hassanelsheikha/varphi_lsp_server
Author: Hassan El-Sheikha
Author-email: hassan.elsheikha@utoronto.ca
Classifier: Programming Language :: Python :: 3
Classifier: License :: OSI Approved :: BSD License
Classifier: Operating System :: OS Independent
License-File: LICENSE
Requires-Dist: varphi_parsing_tools==0.0.4
Requires-Dist: pygls==2.0.0a2
